setup.cfg
setup.py
pants/__init__.py
pants/smart_compile.py
pants_build_utils.egg-info/PKG-INFO
pants_build_utils.egg-info/SOURCES.txt
pants_build_utils.egg-info/dependency_links.txt
pants_build_utils.egg-info/entry_points.txt
pants_build_utils.egg-info/top_level.txt