Metadata-Version: 1.0
Name: pants-build-utils
Version: 0.11
Summary: Stupid pants utils
Home-page: https://www.python.org/sigs/distutils-sig/
Author: David Blackman
Author-email: david@blackmad.com
License: UNKNOWN
Platform: UNKNOWN
